bitwiseai/__init__.py
bitwiseai/bitwiseai.py
bitwiseai/cli.py
bitwiseai/embedding.py
bitwiseai/interfaces.py
bitwiseai/llm.py
bitwiseai/utils.py
bitwiseai/vector_database.py
bitwiseai/core/__init__.py
bitwiseai/core/chat_engine.py
bitwiseai/core/document_manager.py
bitwiseai/core/rag_engine.py
bitwiseai/core/skill_manager.py
bitwiseai/memo/__init__.py
bitwiseai-0.1.2.dist-info/licenses/LICENSE
bitwiseai-0.1.2.dist-info/METADATA
bitwiseai-0.1.2.dist-info/WHEEL
bitwiseai-0.1.2.dist-info/entry_points.txt
bitwiseai-0.1.2.dist-info/top_level.txt
bitwiseai-0.1.2.dist-info/RECORD
