Metadata-Version: 2.4
Name: bitwiseai
Version: 0.1.2
Summary: BitwiseAI - 硬件调试和日志分析的 AI 工具
Home-page: https://github.com/SyJarvis/BitwiseAI
Author-email: SyJarvis <1755115828@qq.com>
Requires-Python: >=3.9
License-File: LICENSE
Requires-Dist: langchain==1.1.0
Requires-Dist: langchain-openai==1.1.0
Requires-Dist: pymilvus>=2.3.0
Requires-Dist: pymilvus[milvus_lite]>=2.3.0
Requires-Dist: numpy>=1.20.0
Requires-Dist: python-dotenv>=1.0.0
Requires-Dist: gradio==6.3.0
Requires-Dist: PyPDF2>=3.0.0
Provides-Extra: dev
Dynamic: home-page
Dynamic: license-file
Dynamic: requires-python
